mac_formatter/__init__.py
mac_formatter/app.py
mac_formatter_gui-0.1.2.dist-info/licenses/LICENSE
mac_formatter_gui-0.1.2.dist-info/METADATA
mac_formatter_gui-0.1.2.dist-info/WHEEL
mac_formatter_gui-0.1.2.dist-info/entry_points.txt
mac_formatter_gui-0.1.2.dist-info/top_level.txt
mac_formatter_gui-0.1.2.dist-info/RECORD
