Metadata-Version: 2.4
Name: mac-formatter-gui
Version: 0.1.2
Summary: A simple Tkinter GUI to format MAC addresses into common styles and copy them to clipboard.
Author-email: Neil Johnson <apps@erudicon.com>
License-Expression: MIT
Project-URL: Homepage, https://erudicon.com/2025/10/12/mac-address-formatter/
Keywords: mac,mac address,formatter,gui,tkinter
Classifier: Programming Language :: Python :: 3
Classifier: Programming Language :: Python :: 3 :: Only
Classifier: Operating System :: OS Independent
Classifier: Environment :: Win32 (MS Windows)
Classifier: Topic :: Utilities
Requires-Python: >=3.8
License-File: LICENSE
Dynamic: license-file
